ControlManual/__init__.py
ControlManual/__main__.py
ControlManual/src/__init__.py
ControlManual/src/check_health.py
ControlManual/src/client.py
ControlManual/src/config.py
ControlManual/src/console.py
ControlManual/src/constants.py
ControlManual/src/error.py
ControlManual/src/info.py
ControlManual/src/logger.py
ControlManual/src/main.py
ControlManual/src/typing.py
ControlManual/src/api/__init__.py
ControlManual/src/api/download_package.py
ControlManual/src/api/is_online.py
ControlManual/src/functions/__init__.py
ControlManual/src/functions/download_github_repo.py
ControlManual/src/functions/load_commands.py
ControlManual/src/functions/load_middleware.py
ControlManual/src/functions/parse.py
ControlManual/src/functions/print_argument_help.py
ControlManual/src/functions/print_command_help.py
ControlManual/src/functions/print_help.py
ControlManual/src/functions/run_exe.py
ControlManual/src/static/__init__.py
ControlManual/src/static/json_file.py
ControlManual/src/static/static_error.py
ControlManual/src/utils/__init__.py
ControlManual/src/utils/error.py
ControlManual/src/utils/format_path.py
ControlManual/src/utils/get_args.py
ControlManual/src/utils/get_path.py
ControlManual/src/utils/success.py
ControlManual/src/utils/title.py
ControlManual-0.0.4.0.dist-info/LICENSE
ControlManual-0.0.4.0.dist-info/METADATA
ControlManual-0.0.4.0.dist-info/WHEEL
ControlManual-0.0.4.0.dist-info/entry_points.txt
ControlManual-0.0.4.0.dist-info/top_level.txt
ControlManual-0.0.4.0.dist-info/RECORD
