Metadata-Version: 2.1
Name: ControlManual
Version: 0.0.4.0
Summary: A universal console-like interface
Home-page: https://github.com/ZeroIntensity/ControlManual
Author: ZeroIntensity
Author-email: admin@controlmanual.xyz
License: UNKNOWN
Project-URL: Bug Tracker, https://github.com/ZeroIntensity/ControlManual/issues
Platform: UNKNOWN
Classifier: Programming Language :: Python :: 3.8
Classifier: Programming Language :: Python :: 3.9
Classifier: Programming Language :: Python :: 3.10
Classifier: License :: OSI Approved :: MIT License
Classifier: Operating System :: OS Independent
Requires-Python: >=3.8
License-File: LICENSE
Requires-Dist: colorama
Requires-Dist: aiohttp
Requires-Dist: click
Requires-Dist: rethread
Requires-Dist: psutil
Requires-Dist: rich
Requires-Dist: distro
Requires-Dist: aiofiles
Requires-Dist: getch
Requires-Dist: watchdog
Requires-Dist: toml
Requires-Dist: py7zr
Requires-Dist: pygithub
